{
  "name": "Pete Ricketts",
  "district": "senator_position_0489.json",
  "party": "Republican",
  "person_wiki_url": "https://en.wikipedia.org/wiki/Pete_Ricketts",
  "votes": {
    "laken_riley": {
      "vote": "Yea",
      "notes": "",
      "points": "-1"
    },
    "hr_1968": {
      "vote": "",
      "points": ""
    }
  },
  "total_points": "",
  "headshot_url": "https://upload.wikimedia.org/wikipedia/commons/b/bd/Sen._Pete_Ricketts_official_portrait%2C_118th_Congress.jpg",
  "headshot_local_url": "static/headshots/pete_ricketts.jpg"
}